dreamplace/__init__.py
dreamplace-0.0.0.dist-info/METADATA
dreamplace-0.0.0.dist-info/WHEEL
dreamplace-0.0.0.dist-info/top_level.txt
dreamplace-0.0.0.dist-info/RECORD
